<?xml version="1.0"?>
<!--Created by Custom Compiler (TM), build , on Mon May  1 15:38:26 2023-->
<file-format name="stateCategory" version="1.0">
 <collection name="analyses">
  <object name="analyses" version="1" type="saAnalysis">
   <attribute value="" name="card" type="giString"/>
   <attribute value="" name="dataDrivenRows" type="giString"/>
   <attribute value="" name="dataDrivenVariables" type="giString"/>
   <attribute value="dc" name="definition" type="giString"/>
   <attribute value="" name="description" type="giString"/>
   <attribute value="" name="designVar" type="giString"/>
   <attribute value="0" name="enabled" type="giBoolean"/>
   <attribute value="0" name="hysteresis" type="giBoolean"/>
   <attribute value="dc" name="name" type="giString"/>
   <attribute value="" name="numPoints" type="giString"/>
   <collection name="options"/>
   <attribute value="" name="poi" type="giString"/>
   <attribute value="/V4" name="source" type="giString"/>
   <attribute value="0" name="start" type="giString"/>
   <attribute value="10n" name="stepSize" type="giString"/>
   <attribute value="800n" name="stop" type="giString"/>
   <attribute value="Source" name="sweep" type="giString"/>
   <attribute value="Linear Steps" name="sweepType" type="giString"/>
   <attribute value="0" name="useCard" type="giBoolean"/>
  </object>
  <object name="analyses" version="1" type="saAnalysis">
   <attribute value="0" name="advanced" type="giBoolean"/>
   <attribute value="" name="card" type="giString"/>
   <attribute value="tran" name="definition" type="giString"/>
   <attribute value="" name="description" type="giString"/>
   <attribute value="0" name="doRestore" type="giBoolean"/>
   <attribute value="0" name="doSave" type="giBoolean"/>
   <attribute value="1" name="enabled" type="giBoolean"/>
   <attribute value="Temp Sweep" name="method" type="giString"/>
   <attribute value="tran" name="name" type="giString"/>
   <attribute value="1" name="numIntervals" type="giString"/>
   <collection name="options"/>
   <attribute value="" name="otherOptions" type="giString"/>
   <attribute value="" name="restorePoint" type="giString"/>
   <attribute value="" name="runLevels" type="giString"/>
   <attribute value="" name="saveList" type="giString"/>
   <attribute value="0" name="soa" type="giBoolean"/>
   <attribute value="0" name="start" type="giString"/>
   <attribute value="10n" name="step" type="giString"/>
   <attribute value="" name="step2" type="giString"/>
   <attribute value="" name="step3" type="giString"/>
   <attribute value="" name="step4" type="giString"/>
   <attribute value="" name="step5" type="giString"/>
   <attribute value="800n" name="stop" type="giString"/>
   <attribute value="" name="stop2" type="giString"/>
   <attribute value="" name="stop3" type="giString"/>
   <attribute value="" name="stop4" type="giString"/>
   <attribute value="" name="stop5" type="giString"/>
   <attribute value="" name="tempStep" type="giString"/>
   <attribute value="" name="tempValues" type="giString"/>
   <attribute value="0" name="uic" type="giBoolean"/>
   <attribute value="0" name="useCard" type="giBoolean"/>
  </object>
 </collection>
</file-format>
